watch.py
bwatch-1.0.5.dist-info/DESCRIPTION.rst
bwatch-1.0.5.dist-info/METADATA
bwatch-1.0.5.dist-info/RECORD
bwatch-1.0.5.dist-info/WHEEL
bwatch-1.0.5.dist-info/entry_points.txt
bwatch-1.0.5.dist-info/metadata.json
bwatch-1.0.5.dist-info/top_level.txt
