Metadata-Version: 2.0
Name: bwatch
Version: 1.0.5
Summary: display a binary watch view in the terminal
Home-page: https://github.com/hellflame/binary_clock/tree/v1.0.5
Author: hellflame
Author-email: hellflamedly@gmail.com
License: MIT
Keywords: binary watch
Platform: UNKNOWN
Classifier: Development Status :: 4 - Beta
Classifier: Environment :: Console
Classifier: Intended Audience :: Developers
Classifier: License :: OSI Approved :: MIT License
Classifier: Operating System :: MacOS :: MacOS X
Classifier: Operating System :: POSIX
Classifier: Programming Language :: Python :: 2.7
Classifier: Programming Language :: Python :: 3.5
Classifier: Programming Language :: Python :: 3.6
Classifier: Programming Language :: Python :: Implementation :: CPython
Classifier: Programming Language :: Python :: Implementation :: PyPy
Classifier: Topic :: Terminals
Classifier: Topic :: Text Processing
